pyoptional/__init__.py
pyoptional/pyoptional.py
pyoptional/pyoptional.pyi
pyjoptional-1.1.2.dist-info/LICENSE
pyjoptional-1.1.2.dist-info/METADATA
pyjoptional-1.1.2.dist-info/WHEEL
pyjoptional-1.1.2.dist-info/top_level.txt
pyjoptional-1.1.2.dist-info/RECORD
