Metadata-Version: 2.1
Name: pyjoptional
Version: 1.1.2
Summary: A Python module providing `PyOptional`, a Java-like `Optional` type for Python 3.9+.
Home-page: https://github.com/cloudstrife9999/pyjoptional
Author: Emanuele Uliana
License: GNU3
Classifier: Programming Language :: Python :: 3
Classifier: Programming Language :: Python :: 3.9
Classifier: Programming Language :: Python :: 3.10
Classifier: Programming Language :: Python :: 3.11
Classifier: Programming Language :: Python :: 3 :: Only
Classifier: Development Status :: 4 - Beta
Classifier: License :: OSI Approved :: GNU General Public License v3 (GPLv3)
Classifier: Operating System :: OS Independent
License-File: LICENSE
Requires-Dist: wheel
